apex_stats/__init__.py
apex_stats/apex.py
apex_stats-0.1.2.dist-info/METADATA
apex_stats-0.1.2.dist-info/WHEEL
apex_stats-0.1.2.dist-info/top_level.txt
apex_stats-0.1.2.dist-info/RECORD
