Metadata-Version: 2.1
Name: apex-stats
Version: 0.1.2
Summary: Tracker.gg api wrapper
Home-page: http://github.com/yamozha/apex_stats
Author: yamozha
Author-email: yamozha16@protonmail.ch
License: MIT
Platform: UNKNOWN
